chatfusion/__init__.py
chatfusion/conf.py
chatfusion/exceptions.py
chatfusion/factories.py
chatfusion/generators.py
chatfusion/model_registry.py
chatfusion/providers.py
chatfusion/responses.py
chatfusion/types.py
chatfusion/prompts/__init__.py
chatfusion/prompts/parts.py
chatfusion/prompts/prompts.py
chatfusion/serializers/__init__.py
chatfusion/serializers/base.py
chatfusion/serializers/prompt_serializers.py
chatfusion-0.1.0.dist-info/LICENSE
chatfusion-0.1.0.dist-info/METADATA
chatfusion-0.1.0.dist-info/WHEEL
chatfusion-0.1.0.dist-info/top_level.txt
chatfusion-0.1.0.dist-info/RECORD
